flake8_exact_pin.py
flake8_exact_pin-0.1.0.dist-info/LICENSE
flake8_exact_pin-0.1.0.dist-info/METADATA
flake8_exact_pin-0.1.0.dist-info/WHEEL
flake8_exact_pin-0.1.0.dist-info/entry_points.txt
flake8_exact_pin-0.1.0.dist-info/top_level.txt
flake8_exact_pin-0.1.0.dist-info/RECORD
