Metadata-Version: 2.1
Name: flake8-exact-pin
Version: 0.1.0
Summary: A flake8 extension that checks for exact pins (e.q.: `foo==1.5.6`) in setup.py
Home-page: https://github.com/msabramo/flake8-exact-pin
Author: Marc Abramowitz
Author-email: msabramo@gmail.com
License: MIT
Keywords: flake8 setup.py pin dependencies
Platform: UNKNOWN
License-File: LICENSE
Requires-Dist: setuptools
